{"0": {"A": 0.0, "B": 0.0, "C": 0.0, "D": 0.0, "E": 0.0, "F": 0.0, "G": 0.0, "H": 0.0, "I": 0.0, "J": 0.0, "Z": 0.0, "OBS": 0.0}}\n{"1": {"A": 0.0, "B": 0.0, "C": 0.0, "D": 0.0, "E": 0.0, "F": 0.0, "G": 0.0, "H": 0.0, "I": 0.0, "J": 0.0, "Z": 0.0, "OBS": 0.0}}\n{"2": {"A": 0.0, "B": 0.0, "C": 0.0, "D": 0.0, "E": 0.0, "F": 0.0, "G": 0.0, "H": 0.0, "I": 0.0, "J": 0.0, "Z": 0.0, "OBS": 0.0}}\n{"3": {"A": 0.0, "B": 0.0, "C": 0.0, "D": 0.0, "E": 0.0, "F": 0.0, "G": 0.0, "H": 0.0, "I": 0.0, "J": 0.0, "Z": 0.0, "OBS": 0.0}}\n{"4": {"A": 0.0, "B": 0.0, "C": 0.0, "D": 0.0, "E": 0.0, "F": 0.0, "G": 0.0, "H": 0.0, "I": 0.0, "J": 0.0, "Z": 0.0, "OBS": 0.0}}\n{"5": {"A": 0.0, "B": 0.0, "C": 0.0, "D": 0.0, "E": 0.0, "F": 0.0, "G": 0.0, "H": 0.0, "I": 0.0, "J": 0.0, "Z": 0.0, "OBS": 0.0}}\n{"6": {"A": 0.0, "B": 0.0, "C": 0.0, "D": 0.0, "E": 0.0, "F": 0.0, "G": 0.0, "H": 0.0, "I": 0.0, "J": 0.0, "Z": 0.0, "OBS": 0.0}}\n{"7": {"A": 0.0, "B": 0.0, "C": 0.0, "D": 0.0, "E": 0.0, "F": 0.0, "G": 0.0, "H": 0.0, "I": 0.0, "J": 0.0, "Z": 0.0, "OBS": 0.0}}\n{"8": {"A": 0.0, "B": 0.0, "C": 0.0, "D": 0.0, "E": 0.0, "F": 0.0, "G": 0.0, "H": 0.0, "I": 0.0, "J": 0.0, "Z": 0.0, "OBS": 0.0}}\n{"9": {"A": 0.0, "B": 0.0, "C": 0.0, "D": 0.0, "E": 0.0, "F": 0.0, "G": 0.0, "H": 0.0, "I": 0.0, "J": 0.0, "Z": 0.0, "OBS": 0.0}}\n{"10": {"A": 0.0, "B": 0.0, "C": 0.0, "D": 0.0, "E": 0.0, "F": 0.0, "G": 0.0, "H": 0.0, "I": 0.0, "J": 0.0, "Z": 0.0, "OBS": 0.0}}\n{"11": {"A": 0.0, "B": 0.0, "C": 0.0, "D": 0.0, "E": 0.0, "F": 0.0, "G": 0.0, "H": 0.0, "I": 0.0, "J": 0.0, "Z": 0.0, "OBS": 0.0}}\n{"12": {"A": 0.0, "B": 0.0, "C": 0.0, "D": 0.0, "E": 0.0, "F": 0.0, "G": 0.0, "H": 0.0, "I": 0.0, "J": 0.0, "Z": 0.0, "OBS": 0.0}}\n{"13": {"A": 0.0, "B": 0.0, "C": 0.0, "D": 0.0, "E": 0.0, "F": 0.0, "G": 0.0, "H": 0.0, "I": 0.0, "J": 0.0, "Z": 0.0, "OBS": 0.0}}\n{"14": {"A": 0.0, "B": 0.0, "C": 0.0, "D": 0.0, "E": 0.0, "F": 0.0, "G": 0.0, "H": 0.0, "I": 0.0, "J": 0.0, "Z": 0.0, "OBS": 0.0}}\n{"15": {"A": 0.0, "B": 0.0, "C": 0.0, "D": 0.0, "E": 0.0, "F": 0.0, "G": 0.0, "H": 0.0, "I": 0.0, "J": 0.0, "Z": 0.0, "OBS": 0.0}}\n{"16": {"A": 0.0, "B": 0.0, "C": 0.0, "D": 0.0, "E": 0.0, "F": 0.0, "G": 0.0, "H": 0.0, "I": 0.0, "J": 0.0, "Z": 0.0, "OBS": 0.0}}\n{"17": {"A": 0.0, "B": 0.0, "C": 0.0, "D": 0.0, "E": 0.0, "F": 0.0, "G": 0.0, "H": 0.0, "I": 0.0, "J": 0.0, "Z": 0.0, "OBS": 0.0}}\n{"18": {"A": 0.0, "B": 0.0, "C": 0.0, "D": 0.0, "E": 0.0, "F": 0.0, "G": 0.0, "H": 0.0, "I": 0.0, "J": 0.0, "Z": 0.0, "OBS": 0.0}}\n{"19": {"A": 0.0, "B": 0.0, "C": 0.0, "D": 0.0, "E": 0.0, "F": 0.0, "G": 0.0, "H": 0.0, "I": 0.0, "J": 0.0, "Z": 0.0, "OBS": 0.0}}\n{"20": {"A": 0.0, "B": 0.0, "C": 0.0, "D": 0.0, "E": 0.0, "F": 0.0, "G": 0.0, "H": 0.0, "I": 0.0, "J": 0.0, "Z": 0.0, "OBS": 0.0}}\n{"21": {"A": 0.0, "B": 0.0, "C": 0.0, "D": 0.0, "E": 0.0, "F": 0.0, "G": 0.0, "H": 0.0, "I": 0.0, "J": 0.0, "Z": 0.0, "OBS": 0.0}}\n{"22": {"A": 0.0, "B": 0.0, "C": 0.0, "D": 0.0, "E": 0.0, "F": 0.0, "G": 0.0, "H": 0.0, "I": 0.0, "J": 0.0, "Z": 0.0, "OBS": 0.0}}\n{"23": {"A": 0.0, "B": 0.0, "C": 0.0, "D": 0.0, "E": 0.0, "F": 0.0, "G": 0.0, "H": 0.0, "I": 0.0, "J": 0.0, "Z": 0.0, "OBS": 0.0}}\n{"24": {"A": 0.0, "B": 0.0, "C": 0.0, "D": 0.0, "E": 0.0, "F": 0.0, "G": 0.0, "H": 0.0, "I": 0.0, "J": 0.0, "Z": 0.0, "OBS": 0.0}}\n{"25": {"A": 0.0, "B": 0.0, "C": 0.0, "D": 0.0, "E": 0.0, "F": 0.0, "G": 0.0, "H": 0.0, "I": 0.0, "J": 0.0, "Z": 0.0, "OBS": 0.0}}\n{"26": {"A": 0.0, "B": 0.0, "C": 0.0, "D": 0.0, "E": 0.0, "F": 0.0, "G": 0.0, "H": 0.0, "I": 0.0, "J": 0.0, "Z": 0.0, "OBS": 0.0}}\n{"27": {"A": 0.0, "B": 0.0, "C": 0.0, "D": 0.0, "E": 0.0, "F": 0.0, "G": 0.0, "H": 0.0, "I": 0.0, "J": 0.0, "Z": 0.0, "OBS": 0.0}}\n{"28": {"A": 0.0, "B": 0.0, "C": 0.0, "D": 0.0, "E": 0.0, "F": 0.0, "G": 0.0, "H": 0.0, "I": 0.0, "J": 0.0, "Z": 0.0, "OBS": 0.0}}\n{"29": {"A": 0.0, "B": 0.0, "C": 0.0, "D": 0.0, "E": 0.0, "F": 0.0, "G": 0.0, "H": 0.0, "I": 0.0, "J": 0.0, "Z": 0.0, "OBS": 0.0}}\n{"30": {"A": 0.0, "B": 0.0, "C": 0.0, "D": 0.0, "E": 0.0, "F": 0.0, "G": 0.0, "H": 0.0, "I": 0.0, "J": 0.0, "Z": 0.0, "OBS": 0.0}}\n{"31": {"A": 0.0, "B": 0.0, "C": 0.0, "D": 0.0, "E": 0.0, "F": 0.0, "G": 0.0, "H": 0.0, "I": 0.0, "J": 0.0, "Z": 0.0, "OBS": 0.0}}\n{"32": {"A": 0.0, "B": 0.0, "C": 0.0, "D": 0.0, "E": 0.0, "F": 0.0, "G": 0.0, "H": 0.0, "I": 0.0, "J": 0.0, "Z": 0.0, "OBS": 0.0}}\n{"33": {"A": 0.0, "B": 0.0, "C": 0.0, "D": 0.0, "E": 0.0, "F": 0.0, "G": 0.0, "H": 0.0, "I": 0.0, "J": 0.0, "Z": 0.0, "OBS": 0.0}}\n{"34": {"A": 0.0, "B": 0.0, "C": 0.0, "D": 0.0, "E": 0.0, "F": 0.0, "G": 0.0, "H": 0.0, "I": 0.0, "J": 0.0, "Z": 0.0, "OBS": 0.0}}\n{"35": {"A": 0.0, "B": 0.0, "C": 0.0, "D": 0.0, "E": 0.0, "F": 0.0, "G": 0.0, "H": 0.0, "I": 0.0, "J": 0.0, "Z": 0.0, "OBS": 0.0}}\n{"36": {"A": 0.0, "B": 0.0, "C": 0.0, "D": 0.0, "E": 0.0, "F": 0.0, "G": 0.0, "H": 0.0, "I": 0.0, "J": 0.0, "Z": 0.0, "OBS": 0.0}}\n{"37": {"A": 0.0, "B": 0.0, "C": 0.0, "D": 0.0, "E": 0.0, "F": 0.0, "G": 0.0, "H": 0.0, "I": 0.0, "J": 0.0, "Z": 0.0, "OBS": 0.0}}\n{"38": {"A": 0.0, "B": 0.0, "C": 0.0, "D": 0.0, "E": 0.0, "F": 0.0, "G": 0.0, "H": 0.0, "I": 0.0, "J": 0.0, "Z": 0.0, "OBS": 0.0}}\n{"39": {"A": 0.0, "B": 0.0, "C": 0.0, "D": 0.0, "E": 0.0, "F": 0.0, "G": 0.0, "H": 0.0, "I": 0.0, "J": 0.0, "Z": 0.0, "OBS": 0.0}}\n{"40": {"A": 0.0, "B": 0.0, "C": 0.0, "D": 0.0, "E": 0.0, "F": 0.0, "G": 0.0, "H": 0.0, "I": 0.0, "J": 0.0, "Z": 0.0, "OBS": 0.0}}\n{"41": {"A": 0.0, "B": 0.0, "C": 0.0, "D": 0.0, "E": 0.0, "F": 0.0, "G": 0.0, "H": 0.0, "I": 0.0, "J": 0.0, "Z": 0.0, "OBS": 0.0}}\n{"42": {"A": 0.0, "B": 0.0, "C": 0.0, "D": 0.0, "E": 0.0, "F": 0.0, "G": 0.0, "H": 0.0, "I": 0.0, "J": 0.0, "Z": 0.0, "OBS": 0.0}}\n{"43": {"A": 0.0, "B": 0.0, "C": 0.0, "D": 0.0, "E": 0.0, "F": 0.0, "G": 0.0, "H": 0.0, "I": 0.0, "J": 0.0, "Z": 0.0, "OBS": 0.0}}\n{"44": {"A": 0.0, "B": 0.0, "C": 0.0, "D": 0.0, "E": 0.0, "F": 0.0, "G": 0.0, "H": 0.0, "I": 0.0, "J": 0.0, "Z": 0.0, "OBS": 0.0}}\n{"45": {"A": 0.0, "B": 0.0, "C": 0.0, "D": 0.0, "E": 0.0, "F": 0.0, "G": 0.0, "H": 0.0, "I": 0.0, "J": 0.0, "Z": 0.0, "OBS": 0.0}}\n{"46": {"A": 0.0, "B": 0.0, "C": 0.0, "D": 0.0, "E": 0.0, "F": 0.0, "G": 0.0, "H": 0.0, "I": 0.0, "J": 0.0, "Z": 0.0, "OBS": 0.0}}\n{"47": {"A": 0.0, "B": 0.0, "C": 0.0, "D": 0.0, "E": 0.0, "F": 0.0, "G": 0.0, "H": 0.0, "I": 0.0, "J": 0.0, "Z": 0.0, "OBS": 0.0}}\n{"48": {"A": 0.0, "B": 0.0, "C": 0.0, "D": 0.0, "E": 0.0, "F": 0.0, "G": 0.0, "H": 0.0, "I": 0.0, "J": 0.0, "Z": 0.0, "OBS": 0.0}}\n{"49": {"A": 0.0, "B": 0.0, "C": 0.0, "D": 0.0, "E": 0.0, "F": 0.0, "G": 0.0, "H": 0.0, "I": 0.0, "J": 0.0, "Z": 0.0, "OBS": 0.0}}\n{"50": {"A": 0.0, "B": 0.0, "C": 0.0, "D": 0.0, "E": 0.0, "F": 0.0, "G": 0.0, "H": 0.0, "I": 0.0, "J": 0.0, "Z": 0.0, "OBS": 0.0}}\n{"51": {"A": 0.0, "B": 0.0, "C": 0.0, "D": 0.0, "E": 0.0, "F": 0.0, "G": 0.0, "H": 0.0, "I": 0.0, "J": 0.0, "Z": 0.0, "OBS": 0.0}}\n{"52": {"A": 0.0, "B": 0.0, "C": 0.0, "D": 0.0, "E": 0.0, "F": 0.0, "G": 0.0, "H": 0.0, "I": 0.0, "J": 0.0, "Z": 0.0, "OBS": 0.0}}\n{"53": {"A": 0.0, "B": 0.0, "C": 0.0, "D": 0.0, "E": 0.0, "F": 0.0, "G": 0.0, "H": 0.0, "I": 0.0, "J": 0.0, "Z": 0.0, "OBS": 0.0}}\n{"54": {"A": 0.0, "B": 0.0, "C": 0.0, "D": 0.0, "E": 0.0, "F": 0.0, "G": 0.0, "H": 0.0, "I": 0.0, "J": 0.0, "Z": 0.0, "OBS": 0.0}}\n{"55": {"A": 0.0, "B": 0.0, "C": 0.0, "D": 0.0, "E": 0.0, "F": 0.0, "G": 0.0, "H": 0.0, "I": 0.0, "J": 0.0, "Z": 0.0, "OBS": 0.0}}\n{"56": {"A": 0.0, "B": 0.0, "C": 0.0, "D": 0.0, "E": 0.0, "F": 0.0, "G": 0.0, "H": 0.0, "I": 0.0, "J": 0.0, "Z": 0.0, "OBS": 0.0}}\n{"57": {"A": 0.0, "B": 0.0, "C": 0.0, "D": 0.0, "E": 0.0, "F": 0.0, "G": 0.0, "H": 0.0, "I": 0.0, "J": 0.0, "Z": 0.0, "OBS": 0.0}}\n{"58": {"A": 0.0, "B": 0.0, "C": 0.0, "D": 0.0, "E": 0.0, "F": 0.0, "G": 0.0, "H": 0.0, "I": 0.0, "J": 0.0, "Z": 0.0, "OBS": 0.0}}\n{"59": {"A": 0.0, "B": 0.0, "C": 0.0, "D": 0.0, "E": 0.0, "F": 0.0, "G": 0.0, "H": 0.0, "I": 0.0, "J": 0.0, "Z": 0.0, "OBS": 0.0}}\n{"60": {"A": 0.0, "B": 0.0, "C": 0.0, "D": 0.0, "E": 0.0, "F": 0.0, "G": 0.0, "H": 0.0, "I": 0.0, "J": 0.0, "Z": 0.0, "OBS": 0.0}}\n{"61": {"A": 0.0, "B": 0.0, "C": 0.0, "D": 0.0, "E": 0.0, "F": 0.0, "G": 0.0, "H": 0.0, "I": 0.0, "J": 0.0, "Z": 0.0, "OBS": 0.0}}\n{"62": {"A": 0.0, "B": 0.0, "C": 0.0, "D": 0.0, "E": 0.0, "F": 0.0, "G": 0.0, "H": 0.0, "I": 0.0, "J": 0.0, "Z": 0.0, "OBS": 0.0}}\n{"63": {"A": 0.0, "B": 0.0, "C": 0.0, "D": 0.0, "E": 0.0, "F": 0.0, "G": 0.0, "H": 0.0, "I": 0.0, "J": 0.0, "Z": 0.0, "OBS": 0.0}}\n{"64": {"A": 0.0, "B": 0.0, "C": 0.0, "D": 0.0, "E": 0.0, "F": 0.0, "G": 0.0, "H": 0.0, "I": 0.0, "J": 0.0, "Z": 0.0, "OBS": 0.0}}\n{"65": {"A": 0.0, "B": 0.0, "C": 0.0, "D": 0.0, "E": 0.0, "F": 0.0, "G": 0.0, "H": 0.0, "I": 0.0, "J": 0.0, "Z": 0.0, "OBS": 0.0}}\n{"66": {"A": 0.0, "B": 0.0, "C": 0.0, "D": 0.0, "E": 0.0, "F": 0.0, "G": 0.0, "H": 0.0, "I": 0.0, "J": 0.0, "Z": 0.0, "OBS": 0.0}}\n{"67": {"A": 0.0, "B": 0.0, "C": 0.0, "D": 0.0, "E": 0.0, "F": 0.0, "G": 0.0, "H": 0.0, "I": 0.0, "J": 0.0, "Z": 0.0, "OBS": 0.0}}\n{"68": {"A": 0.0, "B": 0.0, "C": 0.0, "D": 0.0, "E": 0.0, "F": 0.0, "G": 0.0, "H": 0.0, "I": 0.0, "J": 0.0, "Z": 0.0, "OBS": 0.0}}\n{"69": {"A": 0.0, "B": 0.0, "C": 0.0, "D": 0.0, "E": 0.0, "F": 0.0, "G": 0.0, "H": 0.0, "I": 0.0, "J": 0.0, "Z": 0.0, "OBS": 0.0}}\n{"70": {"A": 0.0, "B": 0.0, "C": 0.0, "D": 0.0, "E": 0.0, "F": 0.0, "G": 0.0, "H": 0.0, "I": 0.0, "J": 0.0, "Z": 0.0, "OBS": 0.0}}\n{"71": {"A": 0.0, "B": 0.0, "C": 0.0, "D": 0.0, "E": 0.0, "F": 0.0, "G": 0.0, "H": 0.0, "I": 0.0, "J": 0.0, "Z": 0.0, "OBS": 0.0}}\n{"72": {"A": 0.0, "B": 0.0, "C": 0.0, "D": 0.0, "E": 0.0, "F": 0.0, "G": 0.0, "H": 0.0, "I": 0.0, "J": 0.0, "Z": 0.0, "OBS": 0.0}}\n{"73": {"A": 0.0, "B": 0.0, "C": 0.0, "D": 0.0, "E": 0.0, "F": 0.0, "G": 0.0, "H": 0.0, "I": 0.0, "J": 0.0, "Z": 0.0, "OBS": 0.0}}\n{"74": {"A": 0.0, "B": 0.0, "C": 0.0, "D": 0.0, "E": 0.0, "F": 0.0, "G": 0.0, "H": 0.0, "I": 0.0, "J": 0.0, "Z": 0.0, "OBS": 0.0}}\n{"75": {"A": 0.0, "B": 0.0, "C": 0.0, "D": 0.0, "E": 0.0, "F": 0.0, "G": 0.0, "H": 0.0, "I": 0.0, "J": 0.0, "Z": 0.0, "OBS": 0.0}}\n{"76": {"A": 0.0, "B": 0.0, "C": 0.0, "D": 0.0, "E": 0.0, "F": 0.0, "G": 0.0, "H": 0.0, "I": 0.0, "J": 0.0, "Z": 0.0, "OBS": 0.0}}\n{"77": {"A": 0.0, "B": 0.0, "C": 0.0, "D": 0.0, "E": 0.0, "F": 0.0, "G": 0.0, "H": 0.0, "I": 0.0, "J": 0.0, "Z": 0.0, "OBS": 0.0}}\n{"78": {"A": 0.0, "B": 0.0, "C": 0.0, "D": 0.0, "E": 0.0, "F": 0.0, "G": 0.0, "H": 0.0, "I": 0.0, "J": 0.0, "Z": 0.0, "OBS": 0.0}}\n{"79": {"A": 0.0, "B": 0.0, "C": 0.0, "D": 0.0, "E": 0.0, "F": 0.0, "G": 0.0, "H": 0.0, "I": 0.0, "J": 0.0, "Z": 0.0, "OBS": 0.0}}\n{"80": {"A": 0.0, "B": 0.0, "C": 0.0, "D": 0.0, "E": 0.0, "F": 0.0, "G": 0.0, "H": 0.0, "I": 0.0, "J": 0.0, "Z": 0.0, "OBS": 0.0}}\n{"81": {"A": 0.0, "B": 0.0, "C": 0.0, "D": 0.0, "E": 0.0, "F": 0.0, "G": 0.0, "H": 0.0, "I": 0.0, "J": 0.0, "Z": 0.0, "OBS": 0.0}}\n{"82": {"A": 0.0, "B": 0.0, "C": 0.0, "D": 0.0, "E": 0.0, "F": 0.0, "G": 0.0, "H": 0.0, "I": 0.0, "J": 0.0, "Z": 0.0, "OBS": 0.0}}\n{"83": {"A": 0.0, "B": 0.0, "C": 0.0, "D": 0.0, "E": 0.0, "F": 0.0, "G": 0.0, "H": 0.0, "I": 0.0, "J": 0.0, "Z": 0.0, "OBS": 0.0}}\n{"84": {"A": 0.0, "B": 0.0, "C": 0.0, "D": 0.0, "E": 0.0, "F": 0.0, "G": 0.0, "H": 0.0, "I": 0.0, "J": 0.0, "Z": 0.0, "OBS": 0.0}}\n{"85": {"A": 0.0, "B": 0.0, "C": 0.0, "D": 0.0, "E": 0.0, "F": 0.0, "G": 0.0, "H": 0.0, "I": 0.0, "J": 0.0, "Z": 0.0, "OBS": 0.0}}\n{"86": {"A": 0.0, "B": 0.0, "C": 0.0, "D": 0.0, "E": 0.0, "F": 0.0, "G": 0.0, "H": 0.0, "I": 0.0, "J": 0.0, "Z": 0.0, "OBS": 0.0}}\n{"87": {"A": 0.0, "B": 0.0, "C": 0.0, "D": 0.0, "E": 0.0, "F": 0.0, "G": 0.0, "H": 0.0, "I": 0.0, "J": 0.0, "Z": 0.0, "OBS": 0.0}}\n{"88": {"A": 0.0, "B": 0.0, "C": 0.0, "D": 0.0, "E": 0.0, "F": 0.0, "G": 0.0, "H": 0.0, "I": 0.0, "J": 0.0, "Z": 0.0, "OBS": 0.0}}\n{"89": {"A": 0.0, "B": 0.0, "C": 0.0, "D": 0.0, "E": 0.0, "F": 0.0, "G": 0.0, "H": 0.0, "I": 0.0, "J": 0.0, "Z": 0.0, "OBS": 0.0}}\n{"90": {"A": 0.0, "B": 0.0, "C": 0.0, "D": 0.0, "E": 0.0, "F": 0.0, "G": 0.0, "H": 0.0, "I": 0.0, "J": 0.0, "Z": 0.0, "OBS": 0.0}}\n{"91": {"A": 0.0, "B": 0.0, "C": 0.0, "D": 0.0, "E": 0.0, "F": 0.0, "G": 0.0, "H": 0.0, "I": 0.0, "J": 0.0, "Z": 0.0, "OBS": 0.0}}\n{"92": {"A": 0.0, "B": 0.0, "C": 0.0, "D": 0.0, "E": 0.0, "F": 0.0, "G": 0.0, "H": 0.0, "I": 0.0, "J": 0.0, "Z": 0.0, "OBS": 0.0}}\n{"93": {"A": 0.0, "B": 0.0, "C": 0.0, "D": 0.0, "E": 0.0, "F": 0.0, "G": 0.0, "H": 0.0, "I": 0.0, "J": 0.0, "Z": 0.0, "OBS": 0.0}}\n{"94": {"A": 0.0, "B": 0.0, "C": 0.0, "D": 0.0, "E": 0.0, "F": 0.0, "G": 0.0, "H": 0.0, "I": 0.0, "J": 0.0, "Z": 0.0, "OBS": 0.0}}\n{"95": {"A": 0.0, "B": 0.0, "C": 0.0, "D": 0.0, "E": 0.0, "F": 0.0, "G": 0.0, "H": 0.0, "I": 0.0, "J": 0.0, "Z": 0.0, "OBS": 0.0}}\n{"96": {"A": 0.0, "B": 0.0, "C": 0.0, "D": 0.0, "E": 0.0, "F": 0.0, "G": 0.0, "H": 0.0, "I": 0.0, "J": 0.0, "Z": 0.0, "OBS": 0.0}}\n{"97": {"A": 0.0, "B": 0.0, "C": 0.0, "D": 0.0, "E": 0.0, "F": 0.0, "G": 0.0, "H": 0.0, "I": 0.0, "J": 0.0, "Z": 0.0, "OBS": 0.0}}\n{"98": {"A": 0.0, "B": 0.0, "C": 0.0, "D": 0.0, "E": 0.0, "F": 0.0, "G": 0.0, "H": 0.0, "I": 0.0, "J": 0.0, "Z": 0.0, "OBS": 0.0}}\n{"99": {"A": 0.0, "B": 0.0, "C": 0.0, "D": 0.0, "E": 0.0, "F": 0.0, "G": 0.0, "H": 0.0, "I": 0.0, "J": 0.0, "Z": 0.0, "OBS": 0.0}}\n{"100": {"A": 0.0, "B": 0.0, "C": 0.0, "D": 0.0, "E": 0.0, "F": 0.0, "G": 0.0, "H": 0.0, "I": 0.0, "J": 0.0, "Z": 0.0, "OBS": 0.0}}\n